cumulative_cost_boosting/__init__.py
cumulative_cost_boosting/AdaCC.py
cumulative_cost_boosting-0.1.2.dist-info/LICENSE
cumulative_cost_boosting-0.1.2.dist-info/METADATA
cumulative_cost_boosting-0.1.2.dist-info/WHEEL
cumulative_cost_boosting-0.1.2.dist-info/RECORD
