Metadata-Version: 2.1
Name: cumulative-cost-boosting
Version: 0.1.2
Summary: Parameter free cost-sensitive adaptive boosting
License: MIT
Author: Dr. Vasileios Iosifidis
Author-email: billiosifidis@gmail.com
Requires-Python: >=3.8,<4.0
Classifier: License :: OSI Approved :: MIT License
Classifier: Programming Language :: Python :: 3
Classifier: Programming Language :: Python :: 3.8
Classifier: Programming Language :: Python :: 3.9
Classifier: Programming Language :: Python :: 3.10
Classifier: Programming Language :: Python :: 3.11
Classifier: Programming Language :: Python :: 3.12
Requires-Dist: imbalanced_learn (>=0.6.2,<0.7.0)
Requires-Dist: imblearn (>=0.0,<0.1)
Requires-Dist: joblib (>=1.2.0,<2.0.0)
Requires-Dist: numpy (>=1.24.4,<2.0.0)
Requires-Dist: pandas (>=1.5.0,<2.0.0)
Requires-Dist: scikit-learn (>=1.0.2,<2.0.0)
Requires-Dist: scipy (>=1.9.3,<2.0.0)
